{
  "version": "7",
  "dialect": "mysql",
  "entries": [
    {
      "idx": 0,
      "version": "5",
      "when": 1762464726471,
      "tag": "0000_good_vindicator",
      "breakpoints": true
    },
    {
      "idx": 1,
      "version": "5",
      "when": 1762464752777,
      "tag": "0001_wise_longshot",
      "breakpoints": true
    },
    {
      "idx": 2,
      "version": "5",
      "when": 1763037447021,
      "tag": "0002_whole_roughhouse",
      "breakpoints": true
    },
    {
      "idx": 3,
      "version": "5",
      "when": 1763509831536,
      "tag": "0003_silly_madame_hydra",
      "breakpoints": true
    }
  ]
}